couplf/__init__.py
couplf/core.py
couplf/util.py
couplf-1.0.2.dist-info/DESCRIPTION.rst
couplf-1.0.2.dist-info/METADATA
couplf-1.0.2.dist-info/RECORD
couplf-1.0.2.dist-info/WHEEL
couplf-1.0.2.dist-info/metadata.json
couplf-1.0.2.dist-info/top_level.txt
couplf-1.0.2.dist-info/zip-safe
